obographs/__init__.py
obographs/contrib.py
obographs/model.py
obographs/py.typed
obographs/standardized.py
obographs/version.py
obographs-0.0.7.dist-info/licenses/LICENSE
obographs-0.0.7.dist-info/WHEEL
obographs-0.0.7.dist-info/entry_points.txt
obographs-0.0.7.dist-info/METADATA
obographs-0.0.7.dist-info/RECORD
